Workbook

Sheet Venta
A1: URBANSIP · Venta a cliente (plantilla)
A2: Copiar este archivo por cada venta: obras/<MODELO>-<CLIENTE>/. Amarillo = completar.
A4: Cliente
A5: Lote / dirección
A6: Localidad
A7: Distancia desde Ituzaingó (km) | B7: 30
A8: Modelo | B8: Aura
A9: Versión | B9: Esencial
A10: Versión de precios del modelo | B10: Aura Esencial v1 · precios al 30/09/26
A11: Superficie cubierta (m²) | B11: 73
A12: Precio por m² del modelo (USD) | B12: 1200 | C12: Esencial 1.200 · Confort 1.500 (ficha)
A13: Fecha de la propuesta
A14: Vendedor
A15: Comisión vendedor | B15: 0.025
A16: Comisión José Luis | B16: 0.01
A18: PRECIO
A19: Precio del modelo | B19: =B11*B12
A20: Cambios aprobados (hoja Cambios) | B20: =Cambios!H40
A21: PRECIO FINAL | B21: =B19+B20
A22: Precio final por m² | B22: =B21/B11
A23: Comisiones (USD) | B23: =B21*(B15+B16)
A25: FORMA DE PAGO (ficha)
A26: Hito | B26: % | C26: Monto (USD) | D26: Fecha prevista | E26: Cobrado
A27: Contratación | B27: 0.1 | C27: =$B$21*B27
A28: Inicio de ejecución | B28: 0.5 | C28: =$B$21*B28
A29: Avance 1 (fundación + kit montado) | B29: 0.15 | C29: =$B$21*B29
A30: Avance 2 (obra gris + instalaciones) | B30: 0.1 | C30: =$B$21*B30
A31: Avance 3 (terminaciones) | B31: 0.1 | C31: =$B$21*B31
A32: Entrega | B32: 0.05 | C32: =$B$21*B32
A33: Total | B33: =SUM(B27:B32) | C33: =SUM(C27:C32)
A35: Cláusula sugerida: "Precio del modelo {Modelo} {Versión}, con precios al {fecha}. Todo cambio se cotiza aparte y se aprueba por escrito, con su precio, antes de ejecutarse."

Sheet Cambios
A1: Planilla de cambios del cliente
A2: Regla: solo suma al precio lo que tiene 'Sí' en Aprobado, con fecha. Precios de la hoja Opcionales o cotización particular.
A4: # | B4: Tipo | C4: Descripción | D4: Un. | E4: Cantidad | F4: Precio unit. (USD) | G4: Total (USD) | H4: Total aprobado (USD) | I4: Aprobado (Sí/No) | J4: Fecha aprobación | K4: Observación
A5: 1 | B5: Terreno | C5: Flete adicional por distancia (más de 50 km) | D5: km | E5: =MAX(0,Venta!B7-50) | F5: =Opcionales!D5 | G5: =IF(E5="","",E5*F5) | H5: =IF(I5="Sí",N(G5),0) | I5: No
A6: 2 | B6: Opcional | C6: Semicubierto / galería | D6: m² | E6: 0 | F6: =Opcionales!D6 | G6: =IF(E6="","",E6*F6) | H6: =IF(I6="Sí",N(G6),0) | I6: No
A7: 3 | B7: Terreno | C7: Diferencia por fundación especial (según estudio de suelos) | D7: gl | E7: 0 | F7: 0 | G7: =IF(E7="","",E7*F7) | H7: =IF(I7="Sí",N(G7),0) | I7: No
A8: 4 | G8: =IF(E8="","",E8*F8) | H8: =IF(I8="Sí",N(G8),0)
A9: 5 | G9: =IF(E9="","",E9*F9) | H9: =IF(I9="Sí",N(G9),0)
A10: 6 | G10: =IF(E10="","",E10*F10) | H10: =IF(I10="Sí",N(G10),0)
A11: 7 | G11: =IF(E11="","",E11*F11) | H11: =IF(I11="Sí",N(G11),0)
A12: 8 | G12: =IF(E12="","",E12*F12) | H12: =IF(I12="Sí",N(G12),0)
A13: 9 | G13: =IF(E13="","",E13*F13) | H13: =IF(I13="Sí",N(G13),0)
A14: 10 | G14: =IF(E14="","",E14*F14) | H14: =IF(I14="Sí",N(G14),0)
A15: 11 | G15: =IF(E15="","",E15*F15) | H15: =IF(I15="Sí",N(G15),0)
A16: 12 | G16: =IF(E16="","",E16*F16) | H16: =IF(I16="Sí",N(G16),0)
A17: 13 | G17: =IF(E17="","",E17*F17) | H17: =IF(I17="Sí",N(G17),0)
A18: 14 | G18: =IF(E18="","",E18*F18) | H18: =IF(I18="Sí",N(G18),0)
A19: 15 | G19: =IF(E19="","",E19*F19) | H19: =IF(I19="Sí",N(G19),0)
... A39: 35 | G39: =IF(E39="","",E39*F39) | H39: =IF(I39="Sí",N(G39),0)
G40: TOTAL APROBADO | H40: =SUM(H5:H39)

Sheet Opcionales
A1: Opcionales de catálogo · precios de venta (USD)
A2: Precio de venta = costo × (1 + recargo) ÷ (1 − comisiones). Recargo a definir por Adrián. | F2: Recargo sobre costo | G2: 0.25
F3: Comisiones | G3: =Venta!B15+Venta!B16
A4: Opcional | B4: Un. | C4: Costo (USD) | D4: Precio venta (USD) | E4: Fuente
A5: Flete adicional por km (más de 50 km) | B5: km | E5: A definir con transportista
A6: Semicubierto / galería | B6: m² | D6: 600 | E6: Ficha: USD 600/m² (precio de venta directo)
A7: Aberturas PVC + mosquiteros (en lugar de aluminio) | B7: gl | C7: 2260 | D7: =C7*(1+$G$2)/(1-$G$3) | E7: Comparación Esencial vs Confort
A8: Aires acondicionados instalados (3 equipos) | B8: gl | C8: 1740 | D8: =C8*(1+$G$2)/(1-$G$3) | E8: Ídem
A9: Anafe + horno empotrado (en lugar de cocina) | B9: gl | C9: 260 | D9: =C9*(1+$G$2)/(1-$G$3) | E9: Ídem
A10: Alacena de cocina | B10: gl | C10: 860 | D10: =C10*(1+$G$2)/(1-$G$3) | E10: Ídem
A11: Mesada de cuarzo | B11: gl | C11: 390 | D11: =C11*(1+$G$2)/(1-$G$3) | E11: Ídem
A12: Pack baño: espejo LED + mampara + accesorios + extractor | B12: gl | C12: 375 | D12: =C12*(1+$G$2)/(1-$G$3) | E12: Ídem
A13: Presurizadora | B13: gl | C13: 225 | D13: =C13*(1+$G$2)/(1-$G$3) | E13: Ídem
A14: Artefactos de iluminación | B14: gl | C14: 370 | D14: =C14*(1+$G$2)/(1-$G$3) | E14: Ídem
A15: Frentes de placard (2 dormitorios) | B15: gl | C15: 775 | D15: =C15*(1+$G$2)/(1-$G$3) | E15: Ídem
A16: Camino perimetral 0,80 m | B16: gl | C16: 1240 | D16: =C16*(1+$G$2)/(1-$G$3) | E16: Ídem
A17: Revestimiento plástico de fachada | B17: gl | C17: 775 | D17: =C17*(1+$G$2)/(1-$G$3) | E17: Ídem
A18: Porcelanato rectificado | B18: gl | C18: 620 | D18: =C18*(1+$G$2)/(1-$G$3) | E18: Ídem
A19: Instalación de gas | B19: gl | E19: Cotización particular (ficha)
A20: Deck de madera | B20: m² | E20: A cotizar

Sheet Flujo de fondos
A1: Flujo de fondos de una casa (Aura Esencial, a precio de ficha)
A2: Supuesto: obra de 4 meses. Costos de Aura_Esencial_Presupuesto_v1 (USD). El kit se paga al inicio. Amarillo = editable.
A4: Concepto | B4: Mes 0 (firma) | C4: Mes 1 | D4: Mes 2 | E4: Mes 3 | F4: Mes 4 (entrega) | G4: Total
A5: COBROS
A6: Contratación 10% | B6: =Venta!$B$21*0.1 | C6: 0 | D6: 0 | E6: 0 | F6: 0 | G6: =SUM(B6:F6)
A7: Inicio 50% | B7: 0 | C7: =Venta!$B$21*0.5 | D7: 0 | E7: 0 | F7: 0 | G7: =SUM(B7:F7)
A8: Avances 15% + 10% + 10% | B8: 0 | C8: =Venta!$B$21*0.15 | D8: =Venta!$B$21*0.1 | E8: =Venta!$B$21*0.1 | F8: 0 | G8: =SUM(B8:F8)
A9: Entrega 5% | B9: 0 | C9: 0 | D9: 0 | E9: 0 | F9: =Venta!$B$21*0.05 | G9: =SUM(B9:F9)
A10: Total cobros | B10: =SUM(B6:B9) | C10: =SUM(C6:C9) | D10: =SUM(D6:D9) | E10: =SUM(E6:E9) | F10: =SUM(F6:F9) | G10: =SUM(G6:G9)
A12: PAGOS
A13: Kit SIPCOR (con IVA) | B13: 0 | C13: 17600 | D13: 0 | E13: 0 | F13: 0 | G13: =SUM(B13:F13)
A14: Flete Córdoba | B14: 0 | C14: 516 | D14: 0 | E14: 0 | F14: 0 | G14: =SUM(B14:F14)
A15: Fundación, contrapisos, mantenimiento y estudio de suelos | B15: 0 | C15: 2000 | D15: 254 | E15: 254 | F15: 0 | G15: =SUM(B15:F15)
A16: Obra gris: techo, siding, zinguería, durlock, sellado | B16: 0 | C16: 0 | D16: 6801 | E16: 0 | F16: 0 | G16: =SUM(B16:F16)
A17: Instalaciones (materiales y artefactos) | B17: 0 | C17: 0 | D17: 2000 | E17: 1869 | F17: 0 | G17: =SUM(B17:F17)
A18: Aberturas y puertas | B18: 0 | C18: 0 | D18: 3226 | E18: 1729 | F18: 0 | G18: =SUM(B18:F18)
A19: Terminaciones, pintura, cocina, mesada, varios | B19: 0 | C19: 0 | D19: 0 | E19: 5982 | F19: 800 | G19: =SUM(B19:F19)
A20: Mano de obra (USD 340/m²) | B20: 0 | C20: 4000 | D20: 8400 | E20: 9000 | F20: 3420 | G20: =SUM(B20:F20)
A21: Comisiones (al cobrar la seña y el inicio) | B21: =Venta!B23*0.5 | C21: =Venta!B23*0.5 | D21: 0 | E21: 0 | F21: 0 | G21: =SUM(B21:F21)
A22: Total pagos | B22: =SUM(B13:B21) | C22: =SUM(C13:C21) | D22: =SUM(D13:D21) | E22: =SUM(E13:E21) | F22: =SUM(F13:F21) | G22: =SUM(G13:G21)
A24: SALDO DEL MES | B24: =B10-B22 | C24: =C10-C22 | D24: =D10-D22 | E24: =E10-E22 | F24: =F10-F22 | G24: =G10-G22
A25: SALDO ACUMULADO | B25: =B24 | C25: =B25+C24 | D25: =C25+D24 | E25: =D25+E24 | F25: =E25+F24
A27: Lectura: si el saldo acumulado nunca es negativo, la obra se financia con el dinero del cliente. Revisar el mes 1: el kit y el 60% del cobro coinciden.
