Workbook

Sheet Datos
A1: URBANSIP · Gestión de obra (método Formosa adaptado a casas SIP)
A2: Una copia por obra, en obras/<MODELO>-<CLIENTE>/. Amarillo = completar.
A4: Obra | B4: Aura Esencial - <Cliente>
A5: Fecha de inicio de obra | B5: 46328
A6: Hoy | B6: =TODAY()
A7: Mano de obra contratada (USD) | B7: 24820
A8: Fondo de garantía | B8: 0.05
A9: Días hábiles por semana | B9: 5
A10: Costo objetivo (USD, del modelo) | B10: 67849

Sheet Plan
A1: Plan de obra · días hábiles con cuadrilla de 3 (planilla 'Mano de obra Aura')
A2: Inicio = día hábil desde el comienzo. Se puede superponer tareas cambiando el inicio. Barras por semana.
A4: Etapa | B4: Tarea | C4: Inicio (día) | D4: Duración (días) | E4: Fin (día) | F4: Fecha inicio | G4: Fecha fin | H4: Jornales | I4: S1 | J4: S2 | K4: S3 | L4: S4 | M4: S5 | N4: S6 | O4: S7 | P4: S8 | Q4: S9 | R4: S10 | S4: S11 | T4: S12 | U4: S13 | V4: S14 | W4: S15 | X4: S16 | Y4: S17 | Z4: S18
A5: 1 Fundación | B5: Replanteo y trabajos preparatorios | C5: 0 | D5: 2 | E5: =C5+D5 | F5: =WORKDAY(Datos!$B$5,C5) | G5: =WORKDAY(Datos!$B$5,E5-1) | H5: =D5*3 | I5: =IF(AND(C5<5,E5>0),1,"") | J5: =IF(AND(C5<10,E5>5),1,"") | K5: =IF(AND(C5<15,E5>10),1,"") | L5: =IF(AND(C5<20,E5>15),1,"") | M5: =IF(AND(C5<25,E5>20),1,"") | N5: =IF(AND(C5<30,E5>25),1,"") | O5: =IF(AND(C5<35,E5>30),1,"") | P5: =IF(AND(C5<40,E5>35),1,"") | Q5: =IF(AND(C5<45,E5>40),1,"") | R5: =IF(AND(C5<50,E5>45),1,"") | S5: =IF(AND(C5<55,E5>50),1,"") | T5: =IF(AND(C5<60,E5>55),1,"") | U5: =IF(AND(C5<65,E5>60),1,"") | V5: =IF(AND(C5<70,E5>65),1,"") | W5: =IF(AND(C5<75,E5>70),1,"") | X5: =IF(AND(C5<80,E5>75),1,"") | Y5: =IF(AND(C5<85,E5>80),1,"") | Z5: =IF(AND(C5<90,E5>85),1,"")
A6: 1 Fundación | B6: Vigas de fundación con pilotines | C6: 2 | D6: 5 | E6: =C6+D6 | F6: =WORKDAY(Datos!$B$5,C6) | G6: =WORKDAY(Datos!$B$5,E6-1) | H6: =D6*3 | I6: =IF(AND(C6<5,E6>0),1,"") | J6: =IF(AND(C6<10,E6>5),1,"") | K6: =IF(AND(C6<15,E6>10),1,"") | L6: =IF(AND(C6<20,E6>15),1,"") | M6: =IF(AND(C6<25,E6>20),1,"") | N6: =IF(AND(C6<30,E6>25),1,"") | O6: =IF(AND(C6<35,E6>30),1,"") | P6: =IF(AND(C6<40,E6>35),1,"") | Q6: =IF(AND(C6<45,E6>40),1,"") | R6: =IF(AND(C6<50,E6>45),1,"") | S6: =IF(AND(C6<55,E6>50),1,"") | T6: =IF(AND(C6<60,E6>55),1,"") | U6: =IF(AND(C6<65,E6>60),1,"") | V6: =IF(AND(C6<70,E6>65),1,"") | W6: =IF(AND(C6<75,E6>70),1,"") | X6: =IF(AND(C6<80,E6>75),1,"") | Y6: =IF(AND(C6<85,E6>80),1,"") | Z6: =IF(AND(C6<90,E6>85),1,"")
A7: 1 Fundación | B7: Contrapiso y carpeta interior | C7: 7 | D7: 3 | E7: =C7+D7 | F7: =WORKDAY(Datos!$B$5,C7) | G7: =WORKDAY(Datos!$B$5,E7-1) | H7: =D7*3 | I7: =IF(AND(C7<5,E7>0),1,"") | J7: =IF(AND(C7<10,E7>5),1,"") | K7: =IF(AND(C7<15,E7>10),1,"") | L7: =IF(AND(C7<20,E7>15),1,"") | M7: =IF(AND(C7<25,E7>20),1,"") | N7: =IF(AND(C7<30,E7>25),1,"") | O7: =IF(AND(C7<35,E7>30),1,"") | P7: =IF(AND(C7<40,E7>35),1,"") | Q7: =IF(AND(C7<45,E7>40),1,"") | R7: =IF(AND(C7<50,E7>45),1,"") | S7: =IF(AND(C7<55,E7>50),1,"") | T7: =IF(AND(C7<60,E7>55),1,"") | U7: =IF(AND(C7<65,E7>60),1,"") | V7: =IF(AND(C7<70,E7>65),1,"") | W7: =IF(AND(C7<75,E7>70),1,"") | X7: =IF(AND(C7<80,E7>75),1,"") | Y7: =IF(AND(C7<85,E7>80),1,"") | Z7: =IF(AND(C7<90,E7>85),1,"")
A8: 2 Kit SIP | B8: Solera base y amure | C8: 10 | D8: 2 | E8: =C8+D8 | F8: =WORKDAY(Datos!$B$5,C8) | G8: =WORKDAY(Datos!$B$5,E8-1) | H8: =D8*3 | I8: =IF(AND(C8<5,E8>0),1,"") | J8: =IF(AND(C8<10,E8>5),1,"") | K8: =IF(AND(C8<15,E8>10),1,"") | L8: =IF(AND(C8<20,E8>15),1,"") | M8: =IF(AND(C8<25,E8>20),1,"") | N8: =IF(AND(C8<30,E8>25),1,"") | O8: =IF(AND(C8<35,E8>30),1,"") | P8: =IF(AND(C8<40,E8>35),1,"") | Q8: =IF(AND(C8<45,E8>40),1,"") | R8: =IF(AND(C8<50,E8>45),1,"") | S8: =IF(AND(C8<55,E8>50),1,"") | T8: =IF(AND(C8<60,E8>55),1,"") | U8: =IF(AND(C8<65,E8>60),1,"") | V8: =IF(AND(C8<70,E8>65),1,"") | W8: =IF(AND(C8<75,E8>70),1,"") | X8: =IF(AND(C8<80,E8>75),1,"") | Y8: =IF(AND(C8<85,E8>80),1,"") | Z8: =IF(AND(C8<90,E8>85),1,"")
A9: 2 Kit SIP | B9: Paneles exteriores | C9: 12 | D9: 6 | E9: =C9+D9 | F9: =WORKDAY(Datos!$B$5,C9) | G9: =WORKDAY(Datos!$B$5,E9-1) | H9: =D9*3 | I9: =IF(AND(C9<5,E9>0),1,"") | J9: =IF(AND(C9<10,E9>5),1,"") | K9: =IF(AND(C9<15,E9>10),1,"") | L9: =IF(AND(C9<20,E9>15),1,"") | M9: =IF(AND(C9<25,E9>20),1,"") | N9: =IF(AND(C9<30,E9>25),1,"") | O9: =IF(AND(C9<35,E9>30),1,"") | P9: =IF(AND(C9<40,E9>35),1,"") | Q9: =IF(AND(C9<45,E9>40),1,"") | R9: =IF(AND(C9<50,E9>45),1,"") | S9: =IF(AND(C9<55,E9>50),1,"") | T9: =IF(AND(C9<60,E9>55),1,"") | U9: =IF(AND(C9<65,E9>60),1,"") | V9: =IF(AND(C9<70,E9>65),1,"") | W9: =IF(AND(C9<75,E9>70),1,"") | X9: =IF(AND(C9<80,E9>75),1,"") | Y9: =IF(AND(C9<85,E9>80),1,"") | Z9: =IF(AND(C9<90,E9>85),1,"")
A10: 2 Kit SIP | B10: Paneles interiores | C10: 18 | D10: 2 | E10: =C10+D10 | F10: =WORKDAY(Datos!$B$5,C10) | G10: =WORKDAY(Datos!$B$5,E10-1) | H10: =D10*3 | I10: =IF(AND(C10<5,E10>0),1,"") | J10: =IF(AND(C10<10,E10>5),1,"") | K10: =IF(AND(C10<15,E10>10),1,"") | L10: =IF(AND(C10<20,E10>15),1,"") | M10: =IF(AND(C10<25,E10>20),1,"") | N10: =IF(AND(C10<30,E10>25),1,"") | O10: =IF(AND(C10<35,E10>30),1,"") | P10: =IF(AND(C10<40,E10>35),1,"") | Q10: =IF(AND(C10<45,E10>40),1,"") | R10: =IF(AND(C10<50,E10>45),1,"") | S10: =IF(AND(C10<55,E10>50),1,"") | T10: =IF(AND(C10<60,E10>55),1,"") | U10: =IF(AND(C10<65,E10>60),1,"") | V10: =IF(AND(C10<70,E10>65),1,"") | W10: =IF(AND(C10<75,E10>70),1,"") | X10: =IF(AND(C10<80,E10>75),1,"") | Y10: =IF(AND(C10<85,E10>80),1,"") | Z10: =IF(AND(C10<90,E10>85),1,"")
A11: 2 Kit SIP | B11: Dinteles, cabios y pintado de MDF | C11: 20 | D11: 3 | E11: =C11+D11 | F11: =WORKDAY(Datos!$B$5,C11) | G11: =WORKDAY(Datos!$B$5,E11-1) | H11: =D11*3 | I11: =IF(AND(C11<5,E11>0),1,"") | J11: =IF(AND(C11<10,E11>5),1,"") | K11: =IF(AND(C11<15,E11>10),1,"") | L11: =IF(AND(C11<20,E11>15),1,"") | M11: =IF(AND(C11<25,E11>20),1,"") | N11: =IF(AND(C11<30,E11>25),1,"") | O11: =IF(AND(C11<35,E11>30),1,"") | P11: =IF(AND(C11<40,E11>35),1,"") | Q11: =IF(AND(C11<45,E11>40),1,"") | R11: =IF(AND(C11<50,E11>45),1,"") | S11: =IF(AND(C11<55,E11>50),1,"") | T11: =IF(AND(C11<60,E11>55),1,"") | U11: =IF(AND(C11<65,E11>60),1,"") | V11: =IF(AND(C11<70,E11>65),1,"") | W11: =IF(AND(C11<75,E11>70),1,"") | X11: =IF(AND(C11<80,E11>75),1,"") | Y11: =IF(AND(C11<85,E11>80),1,"") | Z11: =IF(AND(C11<90,E11>85),1,"")
A12: 2 Kit SIP | B12: Cubierta SIP50 | C12: 23 | D12: 4 | E12: =C12+D12 | F12: =WORKDAY(Datos!$B$5,C12) | G12: =WORKDAY(Datos!$B$5,E12-1) | H12: =D12*3 | I12: =IF(AND(C12<5,E12>0),1,"") | J12: =IF(AND(C12<10,E12>5),1,"") | K12: =IF(AND(C12<15,E12>10),1,"") | L12: =IF(AND(C12<20,E12>15),1,"") | M12: =IF(AND(C12<25,E12>20),1,"") | N12: =IF(AND(C12<30,E12>25),1,"") | O12: =IF(AND(C12<35,E12>30),1,"") | P12: =IF(AND(C12<40,E12>35),1,"") | Q12: =IF(AND(C12<45,E12>40),1,"") | R12: =IF(AND(C12<50,E12>45),1,"") | S12: =IF(AND(C12<55,E12>50),1,"") | T12: =IF(AND(C12<60,E12>55),1,"") | U12: =IF(AND(C12<65,E12>60),1,"") | V12: =IF(AND(C12<70,E12>65),1,"") | W12: =IF(AND(C12<75,E12>70),1,"") | X12: =IF(AND(C12<80,E12>75),1,"") | Y12: =IF(AND(C12<85,E12>80),1,"") | Z12: =IF(AND(C12<90,E12>85),1,"")
A13: 2 Kit SIP | B13: Membranas, alfajías, clavaderas, encintado y botagua | C13: 27 | D13: 4 | E13: =C13+D13 | F13: =WORKDAY(Datos!$B$5,C13) | G13: =WORKDAY(Datos!$B$5,E13-1) | H13: =D13*3 | I13: =IF(AND(C13<5,E13>0),1,"") | J13: =IF(AND(C13<10,E13>5),1,"") | K13: =IF(AND(C13<15,E13>10),1,"") | L13: =IF(AND(C13<20,E13>15),1,"") | M13: =IF(AND(C13<25,E13>20),1,"") | N13: =IF(AND(C13<30,E13>25),1,"") | O13: =IF(AND(C13<35,E13>30),1,"") | P13: =IF(AND(C13<40,E13>35),1,"") | Q13: =IF(AND(C13<45,E13>40),1,"") | R13: =IF(AND(C13<50,E13>45),1,"") | S13: =IF(AND(C13<55,E13>50),1,"") | T13: =IF(AND(C13<60,E13>55),1,"") | U13: =IF(AND(C13<65,E13>60),1,"") | V13: =IF(AND(C13<70,E13>65),1,"") | W13: =IF(AND(C13<75,E13>70),1,"") | X13: =IF(AND(C13<80,E13>75),1,"") | Y13: =IF(AND(C13<85,E13>80),1,"") | Z13: =IF(AND(C13<90,E13>85),1,"")
A14: 3 Obra gris | B14: Chapa y zinguería | C14: 31 | D14: 3 | E14: =C14+D14 | F14: =WORKDAY(Datos!$B$5,C14) | G14: =WORKDAY(Datos!$B$5,E14-1) | H14: =D14*3 | I14: =IF(AND(C14<5,E14>0),1,"") | J14: =IF(AND(C14<10,E14>5),1,"") | K14: =IF(AND(C14<15,E14>10),1,"") | L14: =IF(AND(C14<20,E14>15),1,"") | M14: =IF(AND(C14<25,E14>20),1,"") | N14: =IF(AND(C14<30,E14>25),1,"") | O14: =IF(AND(C14<35,E14>30),1,"") | P14: =IF(AND(C14<40,E14>35),1,"") | Q14: =IF(AND(C14<45,E14>40),1,"") | R14: =IF(AND(C14<50,E14>45),1,"") | S14: =IF(AND(C14<55,E14>50),1,"") | T14: =IF(AND(C14<60,E14>55),1,"") | U14: =IF(AND(C14<65,E14>60),1,"") | V14: =IF(AND(C14<70,E14>65),1,"") | W14: =IF(AND(C14<75,E14>70),1,"") | X14: =IF(AND(C14<80,E14>75),1,"") | Y14: =IF(AND(C14<85,E14>80),1,"") | Z14: =IF(AND(C14<90,E14>85),1,"")
A15: 3 Obra gris | B15: Instalación sanitaria gris | C15: 31 | D15: 3 | E15: =C15+D15 | F15: =WORKDAY(Datos!$B$5,C15) | G15: =WORKDAY(Datos!$B$5,E15-1) | H15: =D15*3 | I15: =IF(AND(C15<5,E15>0),1,"") | J15: =IF(AND(C15<10,E15>5),1,"") | K15: =IF(AND(C15<15,E15>10),1,"") | L15: =IF(AND(C15<20,E15>15),1,"") | M15: =IF(AND(C15<25,E15>20),1,"") | N15: =IF(AND(C15<30,E15>25),1,"") | O15: =IF(AND(C15<35,E15>30),1,"") | P15: =IF(AND(C15<40,E15>35),1,"") | Q15: =IF(AND(C15<45,E15>40),1,"") | R15: =IF(AND(C15<50,E15>45),1,"") | S15: =IF(AND(C15<55,E15>50),1,"") | T15: =IF(AND(C15<60,E15>55),1,"") | U15: =IF(AND(C15<65,E15>60),1,"") | V15: =IF(AND(C15<70,E15>65),1,"") | W15: =IF(AND(C15<75,E15>70),1,"") | X15: =IF(AND(C15<80,E15>75),1,"") | Y15: =IF(AND(C15<85,E15>80),1,"") | Z15: =IF(AND(C15<90,E15>85),1,"")
A16: 3 Obra gris | B16: Instalación eléctrica gris | C16: 34 | D16: 4 | E16: =C16+D16 | F16: =WORKDAY(Datos!$B$5,C16) | G16: =WORKDAY(Datos!$B$5,E16-1) | H16: =D16*3 | I16: =IF(AND(C16<5,E16>0),1,"") | J16: =IF(AND(C16<10,E16>5),1,"") | K16: =IF(AND(C16<15,E16>10),1,"") | L16: =IF(AND(C16<20,E16>15),1,"") | M16: =IF(AND(C16<25,E16>20),1,"") | N16: =IF(AND(C16<30,E16>25),1,"") | O16: =IF(AND(C16<35,E16>30),1,"") | P16: =IF(AND(C16<40,E16>35),1,"") | Q16: =IF(AND(C16<45,E16>40),1,"") | R16: =IF(AND(C16<50,E16>45),1,"") | S16: =IF(AND(C16<55,E16>50),1,"") | T16: =IF(AND(C16<60,E16>55),1,"") | U16: =IF(AND(C16<65,E16>60),1,"") | V16: =IF(AND(C16<70,E16>65),1,"") | W16: =IF(AND(C16<75,E16>70),1,"") | X16: =IF(AND(C16<80,E16>75),1,"") | Y16: =IF(AND(C16<85,E16>80),1,"") | Z16: =IF(AND(C16<90,E16>85),1,"")
... A27: 5 Entrega | B27: Limpieza final y acta de recepción | C27: 62 | D27: 2 | E27: =C27+D27 | F27: =WORKDAY(Datos!$B$5,C27) | G27: =WORKDAY(Datos!$B$5,E27-1) | H27: =D27*3 | I27: =IF(AND(C27<5,E27>0),1,"") | J27: =IF(AND(C27<10,E27>5),1,"") | K27: =IF(AND(C27<15,E27>10),1,"") | L27: =IF(AND(C27<20,E27>15),1,"") | M27: =IF(AND(C27<25,E27>20),1,"") | N27: =IF(AND(C27<30,E27>25),1,"") | O27: =IF(AND(C27<35,E27>30),1,"") | P27: =IF(AND(C27<40,E27>35),1,"") | Q27: =IF(AND(C27<45,E27>40),1,"") | R27: =IF(AND(C27<50,E27>45),1,"") | S27: =IF(AND(C27<55,E27>50),1,"") | T27: =IF(AND(C27<60,E27>55),1,"") | U27: =IF(AND(C27<65,E27>60),1,"") | V27: =IF(AND(C27<70,E27>65),1,"") | W27: =IF(AND(C27<75,E27>70),1,"") | X27: =IF(AND(C27<80,E27>75),1,"") | Y27: =IF(AND(C27<85,E27>80),1,"") | Z27: =IF(AND(C27<90,E27>85),1,"")
B28: TOTAL | E28: =MAX(E5:E27) | H28: =SUM(H5:H27)
B29: Plazo en días corridos | E29: =WORKDAY(Datos!B5,E28)-Datos!B5
B30: Ficha: 90-105 días corridos. Verificar que el plazo dé dentro de ese rango.

Sheet Compras
A1: Compras hacia atrás · necesidad − fabricación − adjudicación − compulsa − documentación
A2: Criterio Formosa: 30 días de documentación (alcance, cómputo, pliego, planos). En un modelo de catálogo la documentación ya está hecha: poner 0 salvo cambios del cliente.
A4: Compra | B4: Para la tarea (fila del Plan) | C4: Fecha de necesidad | D4: Fabricación / entrega (días) | E4: Adjudicar antes de | F4: Compulsa (días) | G4: Pedir cotizaciones el | H4: Documentación (días) | I4: Documentación desde | J4: Estado | K4: Crítica
A5: Kit de paneles SIPCOR + flete | B5: 8 | C5: =INDEX(Plan!$F$1:$F$40,B5) | D5: 30 | E5: =C5-D5 | F5: 5 | G5: =E5-F5 | H5: 0 | I5: =G5-H5 | J5: =IF(I5<Datos!$B$6,"ATRASADA",IF(I5-Datos!$B$6<=7,"ESTA SEMANA","En plazo")) | K5: SÍ: la compra crítica en SIP
A6: Hormigón, hierro y áridos de fundación | B6: 6 | C6: =INDEX(Plan!$F$1:$F$40,B6) | D6: 3 | E6: =C6-D6 | F6: 5 | G6: =E6-F6 | H6: 0 | I6: =G6-H6 | J6: =IF(I6<Datos!$B$6,"ATRASADA",IF(I6-Datos!$B$6<=7,"ESTA SEMANA","En plazo"))
A7: Estudio de suelos | B7: 5 | C7: =INDEX(Plan!$F$1:$F$40,B7) | D7: 10 | E7: =C7-D7 | F7: 3 | G7: =E7-F7 | H7: 0 | I7: =G7-H7 | J7: =IF(I7<Datos!$B$6,"ATRASADA",IF(I7-Datos!$B$6<=7,"ESTA SEMANA","En plazo")) | K7: Antes de definir la fundación
A8: Cabios, alfajías, clavaderas y chapa | B8: 11 | C8: =INDEX(Plan!$F$1:$F$40,B8) | D8: 7 | E8: =C8-D8 | F8: 5 | G8: =E8-F8 | H8: 0 | I8: =G8-H8 | J8: =IF(I8<Datos!$B$6,"ATRASADA",IF(I8-Datos!$B$6<=7,"ESTA SEMANA","En plazo"))
A9: Zinguería a medida | B9: 14 | C9: =INDEX(Plan!$F$1:$F$40,B9) | D9: 10 | E9: =C9-D9 | F9: 5 | G9: =E9-F9 | H9: 0 | I9: =G9-H9 | J9: =IF(I9<Datos!$B$6,"ATRASADA",IF(I9-Datos!$B$6<=7,"ESTA SEMANA","En plazo"))
A10: Aberturas de aluminio (o PVC en Confort) | B10: 17 | C10: =INDEX(Plan!$F$1:$F$40,B10) | D10: 30 | E10: =C10-D10 | F10: 7 | G10: =E10-F10 | H10: 0 | I10: =G10-H10 | J10: =IF(I10<Datos!$B$6,"ATRASADA",IF(I10-Datos!$B$6<=7,"ESTA SEMANA","En plazo")) | K10: Medidas de vanos definidas antes de pedir los paneles
A11: Siding LP | B11: 18 | C11: =INDEX(Plan!$F$1:$F$40,B11) | D11: 7 | E11: =C11-D11 | F11: 5 | G11: =E11-F11 | H11: 0 | I11: =G11-H11 | J11: =IF(I11<Datos!$B$6,"ATRASADA",IF(I11-Datos!$B$6<=7,"ESTA SEMANA","En plazo"))
A12: Placas de yeso y RH | B12: 19 | C12: =INDEX(Plan!$F$1:$F$40,B12) | D12: 5 | E12: =C12-D12 | F12: 3 | G12: =E12-F12 | H12: 0 | I12: =G12-H12 | J12: =IF(I12<Datos!$B$6,"ATRASADA",IF(I12-Datos!$B$6<=7,"ESTA SEMANA","En plazo"))
A13: Materiales sanitarios y eléctricos | B13: 15 | C13: =INDEX(Plan!$F$1:$F$40,B13) | D13: 5 | E13: =C13-D13 | F13: 5 | G13: =E13-F13 | H13: 0 | I13: =G13-H13 | J13: =IF(I13<Datos!$B$6,"ATRASADA",IF(I13-Datos!$B$6<=7,"ESTA SEMANA","En plazo"))
A14: Porcelanato y pegamentos | B14: 21 | C14: =INDEX(Plan!$F$1:$F$40,B14) | D14: 10 | E14: =C14-D14 | F14: 5 | G14: =E14-F14 | H14: 0 | I14: =G14-H14 | J14: =IF(I14<Datos!$B$6,"ATRASADA",IF(I14-Datos!$B$6<=7,"ESTA SEMANA","En plazo"))
A15: Puertas interiores y principal | B15: 22 | C15: =INDEX(Plan!$F$1:$F$40,B15) | D15: 15 | E15: =C15-D15 | F15: 5 | G15: =E15-F15 | H15: 0 | I15: =G15-H15 | J15: =IF(I15<Datos!$B$6,"ATRASADA",IF(I15-Datos!$B$6<=7,"ESTA SEMANA","En plazo"))
A16: Mueble de cocina + mesada | B16: 26 | C16: =INDEX(Plan!$F$1:$F$40,B16) | D16: 30 | E16: =C16-D16 | F16: 7 | G16: =E16-F16 | H16: 0 | I16: =G16-H16 | J16: =IF(I16<Datos!$B$6,"ATRASADA",IF(I16-Datos!$B$6<=7,"ESTA SEMANA","En plazo")) | K16: Medir en obra después del durlock
A17: Artefactos, griferías, termotanque, cocina | B17: 26 | C17: =INDEX(Plan!$F$1:$F$40,B17) | D17: 7 | E17: =C17-D17 | F17: 5 | G17: =E17-F17 | H17: 0 | I17: =G17-H17 | J17: =IF(I17<Datos!$B$6,"ATRASADA",IF(I17-Datos!$B$6<=7,"ESTA SEMANA","En plazo"))
A19: La columna B es el número de fila de la tarea en la hoja Plan (por ejemplo, 9 = Paneles exteriores).

Sheet Certificación
A1: Certificación quincenal de mano de obra · etapas pesadas por jornales
A2: Criterio Formosa: avance por quincena, fondo de garantía 5%. La limpieza se paga con la aprobación de la Dirección de Obra. Adicionales solo con orden escrita previa.
A4: Etapa | B4: Jornales | C4: Peso | D4: Monto etapa (USD) | E4: Q1 % acum. | F4: Q2 % acum. | G4: Q3 % acum. | H4: Q4 % acum. | I4: Q5 % acum. | J4: Q6 % acum.
A5: 1 Fundación | B5: =SUMIF(Plan!$A$5:$A$27,A5,Plan!$H$5:$H$27) | C5: =B5/SUM($B$5:$B$9) | D5: =C5*Datos!$B$7
A6: 2 Kit SIP | B6: =SUMIF(Plan!$A$5:$A$27,A6,Plan!$H$5:$H$27) | C6: =B6/SUM($B$5:$B$9) | D6: =C6*Datos!$B$7
A7: 3 Obra gris | B7: =SUMIF(Plan!$A$5:$A$27,A7,Plan!$H$5:$H$27) | C7: =B7/SUM($B$5:$B$9) | D7: =C7*Datos!$B$7
A8: 4 Terminaciones | B8: =SUMIF(Plan!$A$5:$A$27,A8,Plan!$H$5:$H$27) | C8: =B8/SUM($B$5:$B$9) | D8: =C8*Datos!$B$7
A9: 5 Entrega | B9: =SUMIF(Plan!$A$5:$A$27,A9,Plan!$H$5:$H$27) | C9: =B9/SUM($B$5:$B$9) | D9: =C9*Datos!$B$7
A10: TOTAL | B10: =SUM(B5:B9) | C10: =SUM(C5:C9) | D10: =SUM(D5:D9)
A12: CERTIFICADOS
A13: Concepto | E13: Q1 | F13: Q2 | G13: Q3 | H13: Q4 | I13: Q5 | J13: Q6
A14: Avance acumulado (USD) | E14: =SUMPRODUCT($D$5:$D$9,E5:E9) | F14: =SUMPRODUCT($D$5:$D$9,F5:F9) | G14: =SUMPRODUCT($D$5:$D$9,G5:G9) | H14: =SUMPRODUCT($D$5:$D$9,H5:H9) | I14: =SUMPRODUCT($D$5:$D$9,I5:I9) | J14: =SUMPRODUCT($D$5:$D$9,J5:J9)
A15: Certificado de la quincena (USD) | E15: =E14 | F15: =F14-E14 | G15: =G14-F14 | H15: =H14-G14 | I15: =I14-H14 | J15: =J14-I14
A16: Fondo de garantía 5% (USD) | E16: =-E15*Datos!$B$8 | F16: =-F15*Datos!$B$8 | G16: =-G15*Datos!$B$8 | H16: =-H15*Datos!$B$8 | I16: =-I15*Datos!$B$8 | J16: =-J15*Datos!$B$8
A17: A pagar (USD) | E17: =E15+E16 | F17: =F15+F16 | G17: =G15+G16 | H17: =H15+H16 | I17: =I15+I16 | J17: =J15+J16
A18: Avance acumulado (%) | E18: =E14/Datos!$B$7 | F18: =F14/Datos!$B$7 | G18: =G14/Datos!$B$7 | H18: =H14/Datos!$B$7 | I18: =I14/Datos!$B$7 | J18: =J14/Datos!$B$7
A20: El fondo de garantía acumulado se devuelve con la recepción de la obra.

Sheet Costo objetivo vs real
A1: Control: costo objetivo (modelo) vs real, por rubro
A2: Criterio Formosa: toda compra muestra el objetivo y el desvío. Antes de comparar totales, revisar el alcance ítem por ítem: lo que falta se valúa al precio objetivo.
A4: Rubro | B4: Objetivo (USD) | C4: Comprometido / real (USD) | D4: Desvío (USD) | E4: Desvío % | F4: Proveedor | G4: Observación / alcance faltante
A5: Fundación y contrapisos | B5: 2508 | D5: =IF(C5="","",C5-B5) | E5: =IF(C5="","",D5/B5)
A6: Kit SIPCOR + flete | B6: 18116 | D6: =IF(C6="","",C6-B6) | E6: =IF(C6="","",D6/B6)
A7: Obra gris: techo, siding, zinguería, durlock, sellado | B7: 6801 | D7: =IF(C7="","",C7-B7) | E7: =IF(C7="","",D7/B7)
A8: Instalaciones: materiales y artefactos | B8: 3869 | D8: =IF(C8="","",C8-B8) | E8: =IF(C8="","",D8/B8)
A9: Aberturas y puertas | B9: 4955 | D9: =IF(C9="","",C9-B9) | E9: =IF(C9="","",D9/B9)
A10: Terminaciones, pintura, cocina, mesada, varios | B10: 6782 | D10: =IF(C10="","",C10-B10) | E10: =IF(C10="","",D10/B10)
A11: Mano de obra | B11: 24820 | D11: =IF(C11="","",C11-B11) | E11: =IF(C11="","",D11/B11)
A12: TOTAL | B12: =SUM(B5:B11) | C12: =SUM(C5:C11) | D12: =C12-B12
A14: Ciclo de mejora: al cerrar la obra, un desvío que se repite en 2 o 3 casas corrige el modelo de catálogo (nueva versión v2, v3).

Sheet Adicionales
A1: Registro de adicionales y órdenes de cambio
A2: Regla: ningún adicional se ejecuta sin orden escrita previa con precio. Los del cliente van también a la hoja Cambios de la venta.
A4: # | B4: Fecha | C4: Pedido por (cliente / obra / contratista) | D4: Descripción | E4: Costo (USD) | F4: Precio al cliente (USD) | G4: Orden escrita (Sí/No) | H4: Firmada por | I4: Estado
A5: 1 | I5: =IF(D5="","",IF(G5="Sí","Autorizado","NO EJECUTAR"))
A6: 2 | I6: =IF(D6="","",IF(G6="Sí","Autorizado","NO EJECUTAR"))
A7: 3 | I7: =IF(D7="","",IF(G7="Sí","Autorizado","NO EJECUTAR"))
A8: 4 | I8: =IF(D8="","",IF(G8="Sí","Autorizado","NO EJECUTAR"))
A9: 5 | I9: =IF(D9="","",IF(G9="Sí","Autorizado","NO EJECUTAR"))
A10: 6 | I10: =IF(D10="","",IF(G10="Sí","Autorizado","NO EJECUTAR"))
A11: 7 | I11: =IF(D11="","",IF(G11="Sí","Autorizado","NO EJECUTAR"))
A12: 8 | I12: =IF(D12="","",IF(G12="Sí","Autorizado","NO EJECUTAR"))
A13: 9 | I13: =IF(D13="","",IF(G13="Sí","Autorizado","NO EJECUTAR"))
A14: 10 | I14: =IF(D14="","",IF(G14="Sí","Autorizado","NO EJECUTAR"))
A15: 11 | I15: =IF(D15="","",IF(G15="Sí","Autorizado","NO EJECUTAR"))
A16: 12 | I16: =IF(D16="","",IF(G16="Sí","Autorizado","NO EJECUTAR"))
... A29: 25 | I29: =IF(D29="","",IF(G29="Sí","Autorizado","NO EJECUTAR"))
