Workbook

Sheet Resumen
A1: AURA ESENCIAL · Revisión del costo al 30/09/26
A2: Celdas amarillas: valores que podés cambiar. El resto se calcula solo.
A3: Dólar (BNA venta 30/09/26) | B3: 1550
A4: Superficie cubierta (presupuesto SIPCOR #2790, 08/09/26) | B4: 73
A5: Costo materiales según Excel (ARS) | B5: 82387682
A6: Menos: errores detectados (ver hoja Errores) | B6: =Errores!F8
A7: Costo materiales corregido (ARS) | B7: =B5-B6
A8: Costo materiales corregido (USD) | B8: =B7/B3
A9: Mano de obra llave en mano (u$s/m², planilla MdeO) | B9: 180.29 | C9: Corregido: $20.400.000 de jornales / $1.550 / 73 m². El 263,83 contaba dos veces el montaje del kit.
A10: Mano de obra total (USD) | B10: =B9*B4
A11: COSTO DIRECTO (USD) | B11: =B8+B10
A12: Costo directo por m² (USD) | B12: =B11/B4
A14: Precio de venta Esencial según ficha (USD) | B14: 86400
A15: Diferencia precio − costo directo (USD) | B15: =B14-B11
A16: Diferencia sobre precio (%) | B16: =B15/B14
A18: De esta diferencia todavía hay que restar:
A19: · Comisión de venta (Excel usa 5%) | B19: =B14*B20
A20: % comisión | B20: 0.05
A21: · Faltantes de la ficha Esencial (estimado, ver hoja Faltantes) | B21: =Faltantes!E15
A22: · Proyecto, dirección de obra, logística 50 km, gastos generales | B22: a definir por Adrián
A23: MARGEN ANTES DE GASTOS GENERALES (USD) | B23: =B15-B19-B21
A24: Margen sobre precio (%) | B24: =B23/B14
A27: Ojo: si la mano de obra de instalaciones ya está en el Excel de materiales (ver Errores, punto 4), el costo baja unos USD 2.600 más.

Sheet Errores
A1: Errores de cálculo en 'Aura Costo 30-9-26.xlsx', hoja Materiales
A3: # | B3: Ítem | C3: Cómo está | D3: Cómo debería ser | E3: Importe en Excel (ARS) | F3: Sobrecosto (ARS) | G3: Sobrecosto (USD)
A4: 1 | B4: Contrapiso interior 12 cm | C4: 62,7 m² × $104.207 (es el precio por m³, no por m²) | D4: 62,7 m² × $12.505 por m² (= 7,52 m³ × $104.207) | E4: 6533804 | F4: =E4-62.7*12504.888 | G4: =F4/Resumen!$B$3
A5: 2 | B5: Carpeta de cemento 2 cm (62,7 m²) | C5: Duplicada: además usa el precio del contrapiso exterior | D5: Eliminar: la fila 'Carpeta de cemento' de 88,7 m² ya cubre toda la carpeta | E5: 784056.48 | F5: =E5 | G5: =F5/Resumen!$B$3
A6: 3 | B6: Mesadas granito gris mara | C6: 24 m² × $290.000 | D6: 2,4 m² (4 ml de mueble × 0,60 m) × $290.000 | E6: 6960000 | F6: =E6-2.4*290000 | G6: =F6/Resumen!$B$3
A7: 4 | B7: Kit de paneles SIPCOR | C7: $26.928.565 = USD 17.600,37 al dólar $1.530 (7/9) | D7: USD 17.600,37 al dólar del costo ($1.550) = $27.280.574 | E7: 26928565 | F7: =E7-17600.37*Resumen!B3 | G7: =F7/Resumen!$B$3
E8: TOTAL | F8: =SUM(F4:F7) | G8: =F8/Resumen!B3
A10: A verificar (no se descontó):
A11: 5 | B11: Mano de obra sanitaria y eléctrica | C11: Está en el Excel de materiales ($850.000 + $3.240.000) y la planilla de mano de obra también tiene días de instalaciones. Puede estar contada dos veces (≈ USD 2.640).
A12: 6 | B12: Superficie | C12: Definido: 73 m² cubiertos (presupuesto SIPCOR #2790). El Excel de costos usaba 78 m² y la ficha y la planilla de mano de obra, 72 m². Hay que corregir la ficha.
A13: 7 | B13: Cubierta | C13: Definido por Adrián: paneles SIP 50 de techo (incluidos en el kit SIPCOR: 55 paneles MDF ranurado, con membrana hidrófuga y Easy Band) + cabios de madera + alfajías + clavaderas 2×2 + chapa. El Excel de costos tiene todo eso. OK.
A14: 8 | B14: Sellado adicional ($956.000) | C14: El kit SIPCOR ya incluye cola PUR, espuma de poliuretano, membrana líquida y Flexi Band. La línea 'Materiales de sellado adicionales' del Excel repite casi lo mismo (≈ USD 620).

Sheet Faltantes
A1: Lo que promete la ficha ESENCIAL y no está en el Excel de costos
A2: Montos estimados de referencia (amarillo): reemplazalos por precios reales.
A3: Rubro | B3: Ficha Esencial dice | C3: Excel de costos tiene | D3: Acción | E3: Estimado (USD)
A4: Agua caliente | B4: Termotanque eléctrico Señorial | C4: Nada | D4: Agregar | E4: 250
A5: Cocción | B5: Cocina eléctrica | C5: Nada | D5: Agregar | E5: 450
A6: Climatización | B6: Preinstalación de aire acondicionado | C6: Bocas eléctricas sí; cañerías de cobre/desagüe no | D6: Agregar | E6: 450
A7: Envolvente | B7: Membrana Rothoblaas TRASPIR 110 | C7: Incluida en el kit SIPCOR (membrana hidrófuga + Flexi Band + Easy Band) | D7: OK | E7: 0
A8: Pintura exterior | B8: Siding pintado (la mano de obra lo prevé) | C8: Sin material de pintura exterior | D8: Agregar | E8: 500
A9: Puertas interiores | B9: Placorr moldurada + marco MDF | C9: 'Marco madera' $260.000 c/u | D9: Revisar precio | E9: 0
A10: Puerta exterior | B10: Madera | C10: $1.900.000 | D10: OK, confirmar modelo | E10: 0
A11: Pisos | B11: SPC símil madera o porcelánico | C11: Porcelanato símil madera 19×120 | D11: OK, definir | E11: 0
A12: Proyecto + dirección de obra | B12: Incluidos | C12: Nada | D12: Definir criterio
A13: Logística hasta 50 km | B13: Incluida | C13: Nada | D13: Definir criterio
D15: TOTAL ESTIMADO | E15: =SUM(E4:E13)

Sheet Confort colado
A1: Ítems del Excel que según la ficha son de CONFORT (encarecen el Esencial)
A3: Ítem | B3: Excel de costos | C3: Ficha Esencial | D3: Ficha Confort
A4: Juego de baño | B4: Roca Mónaco | C4: Roca Capea | D4: Roca Mónaco
A5: Espejo | B5: Incluido ($51.000) | C5: No incluye | D5: Espejo LED
A6: Accesorios de baño | B6: Incluidos ($50.000) | C6: No incluye | D6: Incluidos
A7: Extractor baño | B7: Hidra 250 incluido | C7: No incluye | D7: Incluido
A8: Sellado | B8: Flexi Band Rothoblaas ($600.000) | C8: Sellado estándar | D8: Flexi Band / Easy Band
A9: Mueble cocina | B9: 4 ml (diseño con alacena e isla) | C9: Solo bajo mesada | D9: Bajo mesada + alacena
A10: Zócalo | B10: PVC 5 cm | C10: PVC 7 cm | D10: PVC 7 cm
A11: Griferías | B11: FV Alva / Hydros | C11: Hidromet Minicucina / Small | D11: Hidromet Pro Flex / Raptor
A13: Conclusión: el Excel actual está entre Esencial y Confort. Hay que separarlo en dos listas de materiales.
